rot_codec.py
rot_codec-0.1.3.dist-info/licenses/LICENSE
rot_codec-0.1.3.dist-info/METADATA
rot_codec-0.1.3.dist-info/WHEEL
rot_codec-0.1.3.dist-info/entry_points.txt
rot_codec-0.1.3.dist-info/top_level.txt
rot_codec-0.1.3.dist-info/RECORD
