Metadata-Version: 2.4
Name: rot-codec
Version: 0.1.3
Summary: rot5, rot13, rot18, rot47 codecs.
Author: rRR0VrFP
Maintainer: rRR0VrFP
License: MIT
Keywords: rot-codec,gif
Classifier: Development Status :: 5 - Production/Stable
Classifier: Intended Audience :: Developers
Classifier: Topic :: Software Development :: Libraries :: Python Modules
Classifier: License :: OSI Approved :: MIT License
Classifier: Programming Language :: Python :: 3
Classifier: Programming Language :: Python :: 3 :: Only
Requires: click
License-File: LICENSE
Requires-Dist: click
Dynamic: author
Dynamic: classifier
Dynamic: description
Dynamic: description-content-type
Dynamic: keywords
Dynamic: license
Dynamic: license-file
Dynamic: maintainer
Dynamic: requires
Dynamic: requires-dist
Dynamic: summary
